cleeg/__init__.py
cleeg/core.py
cleeg-0.0.1.dist-info/LICENSE
cleeg-0.0.1.dist-info/METADATA
cleeg-0.0.1.dist-info/WHEEL
cleeg-0.0.1.dist-info/top_level.txt
cleeg-0.0.1.dist-info/RECORD
